odoo10_addon_account_check_printing_report_base-10.0.1.2.0-nspkg.pth
odoo/addons/account_check_printing_report_base/README.rst
odoo/addons/account_check_printing_report_base/__init__.py
odoo/addons/account_check_printing_report_base/__manifest__.py
odoo/addons/account_check_printing_report_base/data/account_payment_check_report_data.xml
odoo/addons/account_check_printing_report_base/data/report_paperformat.xml
odoo/addons/account_check_printing_report_base/data/report_paperformat_parameter.xml
odoo/addons/account_check_printing_report_base/i18n/account_check_printing_report_base.pot
odoo/addons/account_check_printing_report_base/models/__init__.py
odoo/addons/account_check_printing_report_base/models/account_journal.py
odoo/addons/account_check_printing_report_base/models/account_payment.py
odoo/addons/account_check_printing_report_base/models/account_payment_check_report.py
odoo/addons/account_check_printing_report_base/models/res_company.py
odoo/addons/account_check_printing_report_base/report/__init__.py
odoo/addons/account_check_printing_report_base/report/account_check_writing_report.xml
odoo/addons/account_check_printing_report_base/report/check_print.py
odoo/addons/account_check_printing_report_base/security/ir.model.access.csv
odoo/addons/account_check_printing_report_base/static/description/icon.png
odoo/addons/account_check_printing_report_base/tests/__init__.py
odoo/addons/account_check_printing_report_base/tests/test_check_printing_report.py
odoo/addons/account_check_printing_report_base/views/account_journal_view.xml
odoo/addons/account_check_printing_report_base/views/account_payment_check_report_view.xml
odoo/addons/account_check_printing_report_base/views/report_check_base.xml
odoo/addons/account_check_printing_report_base/views/res_company_view.xml
odoo10_addon_account_check_printing_report_base-10.0.1.2.0.dist-info/METADATA
odoo10_addon_account_check_printing_report_base-10.0.1.2.0.dist-info/WHEEL
odoo10_addon_account_check_printing_report_base-10.0.1.2.0.dist-info/namespace_packages.txt
odoo10_addon_account_check_printing_report_base-10.0.1.2.0.dist-info/top_level.txt
odoo10_addon_account_check_printing_report_base-10.0.1.2.0.dist-info/RECORD
