Metadata-Version: 2.1
Name: odoo10-addon-account-check-printing-report-base
Version: 10.0.1.2.0
Summary: Account Check Printing Report Base
Home-page: https://github.com/OCA/account-payment
Author: Eficent,Serpent Consulting Services Pvt. Ltd.,Ursa Information Systems,Odoo Community Association (OCA)
Author-email: support@odoo-community.org
License: AGPL-3
Platform: UNKNOWN
Classifier: Programming Language :: Python
Classifier: Framework :: Odoo
Classifier: License :: OSI Approved :: GNU Affero General Public License v3
Requires-Python: ~=2.7
Requires-Dist: odoo10-addon-report-wkhtmltopdf-param
Requires-Dist: odoo (<10.1dev,>=10.0)
